{"complexity":{"averageSentenceLength":null,"averageWordLength":0,"fleschKincaidScore":{"score":0,"message":"Very difficult (College graduate)"},"technicalTermFrequency":{}},"advanced":{"entropy":{"score":0,"message":"This document contains highly repetitive or boilerplate text with very little variation."},"legaClarityScore":{"score":null,"message":"This document is highly complex, with convoluted sentence structures and legal jargon that make it challenging to understand."},"ambiguityScore":{"score":0,"details":{"ambiguousTerms":[],"totalWords":0,"severityLevel":"Very Clear"}},"definitionCoverage":{"coverage":1,"definedTerms":[],"undefinedTerms":[],"stats":{"totalTerms":0,"definedCount":0,"percentageCovered":100}}}}