[{"date":"2024-08-26","agencySlug":"labor-department","title":"2","chapter":"XXIX","section":"421.10","changeType":"addition","sectionsAffected":1,"wordsAdded":134,"wordsRemoved":0,"summary":"Section 421.10 added","significantChange":true},{"date":"2024-08-26","agencySlug":"labor-department","title":"2","chapter":"XXIX","section":"421.400","changeType":"addition","sectionsAffected":1,"wordsAdded":128,"wordsRemoved":0,"summary":"Section 421.400 added","significantChange":true},{"date":"2024-09-16","agencySlug":"labor-department","title":"2","chapter":"XXIX","section":"5900.101","changeType":"addition","sectionsAffected":1,"wordsAdded":92,"wordsRemoved":0,"summary":"Section 5900.101 added","significantChange":true},{"date":"2024-09-17","agencySlug":"labor-department","title":"2","chapter":"XXIX","section":"1800.2","changeType":"addition","sectionsAffected":1,"wordsAdded":82,"wordsRemoved":0,"summary":"Section 1800.2 added","significantChange":true},{"date":"2024-09-17","agencySlug":"labor-department","title":"2","chapter":"XXIX","section":"1800.3","changeType":"addition","sectionsAffected":1,"wordsAdded":362,"wordsRemoved":0,"summary":"Section 1800.3 added","significantChange":true},{"date":"2024-09-17","agencySlug":"labor-department","title":"2","chapter":"XXIX","section":"1800.5","changeType":"addition","sectionsAffected":1,"wordsAdded":64,"wordsRemoved":0,"summary":"Section 1800.5 added","significantChange":true},{"date":"2024-09-17","agencySlug":"labor-department","title":"2","chapter":"XXIX","section":"1800.10","changeType":"addition","sectionsAffected":1,"wordsAdded":146,"wordsRemoved":0,"summary":"Section 1800.10 added","significantChange":true},{"date":"2024-09-17","agencySlug":"labor-department","title":"2","chapter":"XXIX","section":"1800.11","changeType":"addition","sectionsAffected":1,"wordsAdded":436,"wordsRemoved":0,"summary":"Section 1800.11 added","significantChange":true},{"date":"2024-09-17","agencySlug":"labor-department","title":"2","chapter":"XXIX","section":"1800.209","changeType":"addition","sectionsAffected":1,"wordsAdded":48,"wordsRemoved":0,"summary":"Section 1800.209 added","significantChange":true},{"date":"2024-09-17","agencySlug":"labor-department","title":"2","chapter":"XXIX","section":"1800.210","changeType":"addition","sectionsAffected":1,"wordsAdded":51,"wordsRemoved":0,"summary":"Section 1800.210 added","significantChange":true},{"date":"2024-08-15","agencySlug":"labor-department","title":"5","chapter":"XLII","section":"2635.101","changeType":"addition","sectionsAffected":1,"wordsAdded":662,"wordsRemoved":0,"summary":"Section 2635.101 added","significantChange":true},{"date":"2024-08-15","agencySlug":"labor-department","title":"5","chapter":"XLII","section":"2635.102","changeType":"addition","sectionsAffected":1,"wordsAdded":749,"wordsRemoved":0,"summary":"Section 2635.102 added","significantChange":true},{"date":"2024-08-15","agencySlug":"labor-department","title":"5","chapter":"XLII","section":"2635.103","changeType":"addition","sectionsAffected":1,"wordsAdded":102,"wordsRemoved":0,"summary":"Section 2635.103 added","significantChange":true},{"date":"2024-08-15","agencySlug":"labor-department","title":"5","chapter":"XLII","section":"2635.104","changeType":"addition","sectionsAffected":1,"wordsAdded":369,"wordsRemoved":0,"summary":"Section 2635.104 added","significantChange":true},{"date":"2024-08-15","agencySlug":"labor-department","title":"5","chapter":"XLII","section":"2635.105","changeType":"addition","sectionsAffected":1,"wordsAdded":400,"wordsRemoved":0,"summary":"Section 2635.105 added","significantChange":true},{"date":"2024-08-15","agencySlug":"labor-department","title":"5","chapter":"XLII","section":"2635.106","changeType":"addition","sectionsAffected":1,"wordsAdded":210,"wordsRemoved":0,"summary":"Section 2635.106 added","significantChange":true},{"date":"2024-08-15","agencySlug":"labor-department","title":"5","chapter":"XLII","section":"2635.107","changeType":"addition","sectionsAffected":1,"wordsAdded":266,"wordsRemoved":0,"summary":"Section 2635.107 added","significantChange":true},{"date":"2024-08-15","agencySlug":"labor-department","title":"5","chapter":"XLII","section":"2635.201","changeType":"addition","sectionsAffected":1,"wordsAdded":438,"wordsRemoved":0,"summary":"Section 2635.201 added","significantChange":true},{"date":"2024-08-15","agencySlug":"labor-department","title":"5","chapter":"XLII","section":"2635.202","changeType":"addition","sectionsAffected":1,"wordsAdded":290,"wordsRemoved":0,"summary":"Section 2635.202 added","significantChange":true},{"date":"2024-08-15","agencySlug":"labor-department","title":"5","chapter":"XLII","section":"2635.203","changeType":"addition","sectionsAffected":1,"wordsAdded":2375,"wordsRemoved":0,"summary":"Section 2635.203 added","significantChange":true},{"date":"2024-08-22","agencySlug":"labor-department","title":"41","chapter":"50","section":"102-5.30","changeType":"addition","sectionsAffected":1,"wordsAdded":498,"wordsRemoved":0,"summary":"Section 102-5.30 added","significantChange":true},{"date":"2024-08-22","agencySlug":"labor-department","title":"41","chapter":"50","section":"102-5.35","changeType":"addition","sectionsAffected":1,"wordsAdded":116,"wordsRemoved":0,"summary":"Section 102-5.35 added","significantChange":true},{"date":"2024-08-22","agencySlug":"labor-department","title":"41","chapter":"50","section":"102-5.70","changeType":"addition","sectionsAffected":1,"wordsAdded":103,"wordsRemoved":0,"summary":"Section 102-5.70 added","significantChange":true},{"date":"2024-08-22","agencySlug":"labor-department","title":"41","chapter":"50","section":"102-5.75","changeType":"addition","sectionsAffected":1,"wordsAdded":190,"wordsRemoved":0,"summary":"Section 102-5.75 added","significantChange":true},{"date":"2024-08-22","agencySlug":"labor-department","title":"41","chapter":"50","section":"102-5.90","changeType":"addition","sectionsAffected":1,"wordsAdded":90,"wordsRemoved":0,"summary":"Section 102-5.90 added","significantChange":true},{"date":"2024-08-22","agencySlug":"labor-department","title":"41","chapter":"50","section":"102-5.105","changeType":"addition","sectionsAffected":1,"wordsAdded":131,"wordsRemoved":0,"summary":"Section 102-5.105 added","significantChange":true},{"date":"2024-08-22","agencySlug":"labor-department","title":"41","chapter":"50","section":"102-36.5","changeType":"addition","sectionsAffected":1,"wordsAdded":96,"wordsRemoved":0,"summary":"Section 102-36.5 added","significantChange":true},{"date":"2024-08-22","agencySlug":"labor-department","title":"41","chapter":"50","section":"102-36.40","changeType":"addition","sectionsAffected":1,"wordsAdded":1273,"wordsRemoved":0,"summary":"Section 102-36.40 added","significantChange":true},{"date":"2024-08-22","agencySlug":"labor-department","title":"41","chapter":"50","section":"102-36.60","changeType":"addition","sectionsAffected":1,"wordsAdded":96,"wordsRemoved":0,"summary":"Section 102-36.60 added","significantChange":true},{"date":"2024-08-22","agencySlug":"labor-department","title":"41","chapter":"50","section":"102-36.115","changeType":"addition","sectionsAffected":1,"wordsAdded":104,"wordsRemoved":0,"summary":"Section 102-36.115 added","significantChange":true},{"date":"2024-08-15","agencySlug":"labor-department","title":"48","chapter":"29","section":"211.271","changeType":"addition","sectionsAffected":1,"wordsAdded":40,"wordsRemoved":0,"summary":"Section 211.271 added","significantChange":true},{"date":"2024-08-15","agencySlug":"labor-department","title":"48","chapter":"29","section":"212.207","changeType":"addition","sectionsAffected":1,"wordsAdded":237,"wordsRemoved":0,"summary":"Section 212.207 added","significantChange":true},{"date":"2024-08-15","agencySlug":"labor-department","title":"48","chapter":"29","section":"212.301","changeType":"addition","sectionsAffected":1,"wordsAdded":3987,"wordsRemoved":0,"summary":"Section 212.301 added","significantChange":true},{"date":"2024-08-15","agencySlug":"labor-department","title":"48","chapter":"29","section":"223.107-1","changeType":"addition","sectionsAffected":1,"wordsAdded":21,"wordsRemoved":0,"summary":"Section 223.107-1 added","significantChange":true},{"date":"2024-08-15","agencySlug":"labor-department","title":"48","chapter":"29","section":"223.107-4","changeType":"addition","sectionsAffected":1,"wordsAdded":137,"wordsRemoved":0,"summary":"Section 223.107-4 added","significantChange":true},{"date":"2024-08-15","agencySlug":"labor-department","title":"48","chapter":"29","section":"223.302","changeType":"addition","sectionsAffected":1,"wordsAdded":56,"wordsRemoved":0,"summary":"Section 223.302 added","significantChange":true},{"date":"2024-08-15","agencySlug":"labor-department","title":"48","chapter":"29","section":"223.304","changeType":"addition","sectionsAffected":1,"wordsAdded":49,"wordsRemoved":0,"summary":"Section 223.304 added","significantChange":true},{"date":"2024-08-15","agencySlug":"labor-department","title":"48","chapter":"29","section":"225.7003-3","changeType":"addition","sectionsAffected":1,"wordsAdded":1452,"wordsRemoved":0,"summary":"Section 225.7003-3 added","significantChange":true},{"date":"2024-08-15","agencySlug":"labor-department","title":"48","chapter":"29","section":"225.7018-3","changeType":"addition","sectionsAffected":1,"wordsAdded":438,"wordsRemoved":0,"summary":"Section 225.7018-3 added","significantChange":true},{"date":"2024-08-15","agencySlug":"labor-department","title":"48","chapter":"29","section":"226.570","changeType":"addition","sectionsAffected":1,"wordsAdded":10,"wordsRemoved":0,"summary":"Section 226.570 added","significantChange":true}]